{"name":"wktpsvp8","1":{"time":1634035607},"2":{"time":1634035628},"3":{"time":1634036886},"4":{"text":"","conf":"0","sliders":[],"ranks":[],"choices":["Becher C","Becher B","Becher A","Becher D"],"time":1634037079},"5":{"text":"0.37","conf":"100","sliders":[],"ranks":[],"choices":[],"time":1634037163},"6":{"text":"1.59","conf":"100","sliders":[],"ranks":[],"choices":[],"time":1634037208},"7":{"text":"0.96","conf":"100","sliders":[],"ranks":[],"choices":[],"time":1634037231},"8":{"text":"0.8","conf":"100","sliders":[],"ranks":[],"choices":[],"time":1634037273},"9":{"text":"","conf":"","sliders":["0","10","80","10"],"ranks":[],"choices":[],"time":1634037383},"10":{"text":"","conf":"","sliders":["80","10","0","10"],"ranks":[],"choices":[],"time":1634037399},"11":{"text":"","conf":"","sliders":["10","0","10","80"],"ranks":[],"choices":[],"time":1634037461},"12":{"text":"","conf":"","sliders":["10","0","10","80"],"ranks":[],"choices":[],"time":1634037518},"13":{"text":"A = \u03b5 * l * C","conf":"100","sliders":[],"ranks":[],"choices":[],"time":1634037583},"14":{"text":"","conf":"","sliders":[],"ranks":[],"choices":["","","",""],"time":1634037614},"15":{"text":"Oui","conf":"","sliders":[],"ranks":[],"choices":[],"time":1634037622},"16":{"time":1634037633},"17":{"text":"","conf":"0","sliders":[],"ranks":[],"choices":["Je ne sais pas","Je ne sais pas","Je ne sais pas"],"time":1634037693},"feedback":{"s_entertain":"75","s_difficult":"75","t_good":"-","t_bad":"-","t_what":"-","time":1634037854},"19":{"time":1634037859}}