{"name":"39htvmt5","1":{"time":1620814066},"2":{"time":1620814299},"3":{"time":1620814657},"4":{"sliders":[],"ranks":["3","0","2","1"],"time":1620814692},"5":{"text":"0,74","conf":"10","sliders":[],"ranks":[],"choices":[],"time":1620814745},"6":{"text":"0,53","conf":"10","sliders":[],"ranks":[],"choices":[],"time":1620814757},"7":{"text":"0,96","conf":"10","sliders":[],"ranks":[],"choices":[],"time":1620814768},"8":{"text":"0,60","conf":"10","sliders":[],"ranks":[],"choices":[],"time":1620814777},"9":{"text":"","conf":"","sliders":["60","25","10","5"],"ranks":[],"choices":[],"time":1620814834},"10":{"text":"","conf":"","sliders":["15","15","30","40"],"ranks":[],"choices":[],"time":1620814892},"11":{"text":"Da jedes individuell einstellbar ist k\u00f6nnen somit auch viele verschiedene Resultate hervorgehen. Wenn man die Breite ver\u00e4ndert kann man somit mehr in den Becher f\u00fcllen. Wenn der Becher also ver\u00e4ndert wird, die Konzentration aber nicht wird diese auf ein gr\u00f6sseres Volumen bestehen bleiben. ","conf":"5","sliders":[],"ranks":[],"choices":[],"time":1620815132},"12":{"text":"","conf":"","sliders":[],"ranks":[],"choices":["Wertangaben die ich verglichen habe um dann n\u00f6tige Informationen daraus zu entnehmen.",null,null,null],"time":1620815229},"13":{"text":"Ich habe davor nichts mit diesem Gesetz zu tun gehabt. Somit war mir alles neu.","conf":"","sliders":[],"ranks":[],"choices":[],"time":1620815302},"14":{"time":1620815528},"15":{"text":"","conf":"0","sliders":[],"ranks":[],"choices":["NiCl2: Nickel (II) chromate","K2Cr2O7: Potassium dichromate","Ich weiss nicht"],"time":1620815543},"feedback":{"s_entertain":"0","s_difficult":"100","t_good":"Die zeitliche Einteilung der Aufgaben war fair.","t_bad":"Die Aufgabenstellung war mir nicht wirklich klar. Ich verstand nicht was ich tun musste.","t_what":"Eher nein. Ich habe mir nicht gen\u00fcgend Informationen aufgeschrieben um in den nachfolgenden Aufgaben gute Antworten geben zu k\u00f6nnen.","time":1620815714},"17":{"time":1620815720}}