{"name":"wu7kdm6q","1":{"time":1620814035},"2":{"time":1620814117},"3":{"time":1620814181},"4":{"sliders":[],"ranks":["0","3","1","2"],"time":1620814270},"5":{"text":"0.37","conf":"50","sliders":[],"ranks":[],"choices":[],"time":1620814323},"6":{"text":"1.59","conf":"0","sliders":[],"ranks":[],"choices":[],"time":1620814355},"7":{"text":"0.95","conf":"50","sliders":[],"ranks":[],"choices":[],"time":1620814399},"8":{"text":"0.2","conf":"35","sliders":[],"ranks":[],"choices":[],"time":1620814447},"9":{"text":"","conf":"","sliders":["0","0","100","0"],"ranks":[],"choices":[],"time":1620814512},"10":{"text":"","conf":"","sliders":["0","100","0","0"],"ranks":[],"choices":[],"time":1620814711},"11":{"text":"E =h*f = (h*c)\/ w\u00e4llen l\u00e4nge","conf":"100","sliders":[],"ranks":[],"choices":[],"time":1620815026},"12":{"text":"","conf":"","sliders":[],"ranks":[],"choices":[null,null,null,null],"time":1620815041},"13":{"text":"Habe Erinnerungen daran von Schulzeiten","conf":"","sliders":[],"ranks":[],"choices":[],"time":1620815074},"14":{"time":1620815097},"15":{"text":"","conf":"0","sliders":[],"ranks":[],"choices":["Ich weiss nicht","Ich weiss nicht","Ich weiss nicht"],"time":1620815149},"feedback":{"s_entertain":"55","s_difficult":"65","t_good":"Die Simulationen sind hilfreich","t_bad":"Es stockte manchmal und man brauchte lang von seite 1 zu 2 zu kommen","t_what":"ich war nicht vorbereitet und ist eher l\u00e4nger her das ic etwas mit uv Spektroskopie zu tun hatte","time":1620815358},"17":{"time":1620815360}}