{"name":"uhq3p7yr","1":{"time":1624346139},"2":{"time":1624346150},"3":{"time":1624346259},"4":{"text":"","conf":"70","sliders":[],"ranks":[],"choices":["Becher D","Becher A","Becher B","Becher C"],"time":1624346292},"5":{"text":"1.48","conf":"60","sliders":[],"ranks":[],"choices":[],"time":1624346324},"6":{"text":"1.59","conf":"60","sliders":[],"ranks":[],"choices":[],"time":1624346403},"7":{"text":"1.92","conf":"35","sliders":[],"ranks":[],"choices":[],"time":1624346541},"8":{"text":"2.4","conf":"75","sliders":[],"ranks":[],"choices":[],"time":1624346581},"9":{"text":"","conf":"","sliders":["60","0","40","0"],"ranks":[],"choices":[],"time":1624346633},"10":{"text":"","conf":"","sliders":["0","60","40","0"],"ranks":[],"choices":[],"time":1624346705},"11":{"text":"Die Wellenl\u00e4nge des Lichtstrahls wird beeinflusst von der Konzentration des Bechers, sowie die Breite des Bechers.\r\n\r\nJe breiter der Becher, desto gr\u00f6sser die Extinktion","conf":"85","sliders":[],"ranks":[],"choices":[],"time":1624346903},"12":{"text":"","conf":"","sliders":[],"ranks":[],"choices":["","","",""],"time":1624346917},"13":{"text":"Garnicht, allerdings mit logischem verst\u00e4ndnis bin ich auf eine Antwort gekommen. Ob die Antwort richtig ist, ist fraglich","conf":"","sliders":[],"ranks":[],"choices":[],"time":1624347005},"14":{"time":1624347890},"15":{"text":"","conf":"50","sliders":[],"ranks":[],"choices":["Co(No3)2: Cobalt (II) nitrate","CoCl2: Cobalt chloride","CuSO4: Copper sulfate"],"time":1624347917},"feedback":{"s_entertain":"65","s_difficult":"35","t_good":"Besonders gut fand ich, dass Sie einen Psychischen Test mit einem Thema verkn\u00fcpft haben, wovon die Sch\u00fcler keine Ahnung haben. So mussten sie ihre eigene Art und Weise herausfinden was nat\u00fcrlich auch ins negative beurteilt wurde","t_bad":"Schlecht fand ich, dass die Aufgaben nicht verst\u00e4ndlich genug waren. Ich zum Beispiel bin davon \u00fcberzeugt dass ich die Aufgaben gel\u00f6st h\u00e4tte, wenn mir mehr \"Eselsbr\u00fccken\" zur verf\u00fcgung gestellt worden w\u00e4ren.","t_what":"Es war der Instinkt eines Menschen wie man es in der Vergangenheit immer am besten gel\u00f6st hatte. Meine eigene L\u00f6sungsstrategie beurteile ich wie aus der Hand gegriffen, da es ein Thema war, was ich davor noch nicht geh\u00f6rt hatte. Besser k\u00f6nnte ich es machen wenn sie mir ein Praktikum anbieten wo ich meine F\u00e4higkeiten unter Beweis stellen kann.","time":1624348389},"17":{"time":1624348392}}