{"name":"mjh6emdj","1":{"text":"1234","conf":"80","sliders":[],"ranks":[],"time":1619434435},"2":{"text":"123123","conf":"35","sliders":[],"ranks":[],"time":1619434438},"3":{"text":"123123","conf":"50","sliders":[],"ranks":[],"time":1619434443},"4":{"text":"12313","conf":"65","sliders":[],"ranks":[],"time":1619434446},"5":{"text":"","conf":"","sliders":["60","40","0","0"],"ranks":[],"time":1619434472},"6":{"text":"","conf":"","sliders":["100","0","0","0"],"ranks":[],"time":1619434480},"7":{"text":"asdasd","conf":"40","sliders":[],"ranks":[],"time":1619434485},"8":{"text":"asdasd","conf":"","sliders":[],"ranks":[],"time":1619434488},"feedback":{"s_entertain":"30","s_difficult":"30","t_good":"qwewqe","t_bad":"qweqwe","t_what":"qwewqe","time":1619434547}}